whatsapp/__init__.py
whatsapp/_version.py
whatsapp/bot.py
whatsapp/config_account.py
whatsapp/crypto.py
whatsapp/error.py
whatsapp/file_handler.py
whatsapp/messages.py
whatsapp/utils.py
python_whatsapp_wrapper-0.1.10.dist-info/LICENSE
python_whatsapp_wrapper-0.1.10.dist-info/METADATA
python_whatsapp_wrapper-0.1.10.dist-info/WHEEL
python_whatsapp_wrapper-0.1.10.dist-info/top_level.txt
python_whatsapp_wrapper-0.1.10.dist-info/RECORD
