Metadata-Version: 2.1
Name: python-whatsapp-wrapper
Version: 0.1.10
Summary: Pure python project for META Whatsapp Business API wrapper.
Author-email: Sergio Pires <sergiodanpires@gmail.com>
License: MIT License
Project-URL: repository, https://www.github.com/Sergio-Daniel-Pires/python-whatsapp-wrapper
Keywords: python,whatsapp,wrapper,api
Classifier: Programming Language :: Python
Classifier: Programming Language :: Python :: 3.10
Classifier: Programming Language :: Python :: 3.11
Classifier: Programming Language :: Python :: 3.12
Requires-Python: >=3.10
License-File: LICENSE
Requires-Dist: flask>=3.0.3
Requires-Dist: dataclasses_json>=0.6.6
Requires-Dist: cryptography>=43.0.3
Requires-Dist: pycryptodome>=3.21.0
Requires-Dist: httpx>=0.27.0
Provides-Extra: test
Requires-Dist: pytest>=1.0.0; extra == "test"
Requires-Dist: pre-commit>=3.7.1; extra == "test"
Requires-Dist: isort>=5.13.2; extra == "test"
Requires-Dist: pytest-asyncio>=0.23.5; extra == "test"
Provides-Extra: docs
Requires-Dist: sphinx>=8.0.2; extra == "docs"
Requires-Dist: furo>=2024.8.6; extra == "docs"
Requires-Dist: sphinx_copybutton>=0.5.2; extra == "docs"
